paddleocr_cli/__init__.py
paddleocr_cli/main.py
paddleocr_cli/mcp_server.py
paddleocr_mcp_server-0.1.0.dist-info/METADATA
paddleocr_mcp_server-0.1.0.dist-info/WHEEL
paddleocr_mcp_server-0.1.0.dist-info/entry_points.txt
paddleocr_mcp_server-0.1.0.dist-info/licenses/LICENSE
paddleocr_mcp_server-0.1.0.dist-info/RECORD
