Metadata-Version: 2.4
Name: paddleocr-mcp-server
Version: 0.1.0
Summary: PaddleOCR MCP server - Extract text from images using PaddleOCR with optimized performance
Project-URL: Homepage, https://github.com/yourusername/PaddleOCR-MCP
Project-URL: Documentation, https://github.com/yourusername/PaddleOCR-MCP#readme
Project-URL: Repository, https://github.com/yourusername/PaddleOCR-MCP
Project-URL: Issues, https://github.com/yourusername/PaddleOCR-MCP/issues
Author: PaddleOCR-MCP Contributors
License: MIT
License-File: LICENSE
Keywords: image-processing,mcp,model-context-protocol,ocr,paddleocr,text-recognition
Classifier: Development Status :: 4 - Beta
Classifier: Intended Audience :: Developers
Classifier: License :: OSI Approved :: MIT License
Classifier: Programming Language :: Python :: 3
Classifier: Programming Language :: Python :: 3.8
Classifier: Programming Language :: Python :: 3.9
Classifier: Programming Language :: Python :: 3.10
Classifier: Programming Language :: Python :: 3.11
Classifier: Programming Language :: Python :: 3.12
Classifier: Topic :: Scientific/Engineering :: Image Recognition
Classifier: Topic :: Software Development :: Libraries :: Python Modules
Requires-Python: >=3.8
Requires-Dist: paddleocr>=2.7.0
Requires-Dist: paddlepaddle>=2.5.0
Requires-Dist: pillow>=10.0.0
